openclean_pattern/__init__.py
openclean_pattern/config.py
openclean_pattern/opencleanpatternfinder.py
openclean_pattern/version.py
openclean_pattern/align/__init__.py
openclean_pattern/align/base.py
openclean_pattern/align/combinatorics.py
openclean_pattern/align/factory.py
openclean_pattern/align/needlemanwunsch.py
openclean_pattern/align/pad.py
openclean_pattern/align/progressive.py
openclean_pattern/align/smart.py
openclean_pattern/align/distance/__init__.py
openclean_pattern/align/distance/absolute.py
openclean_pattern/align/distance/base.py
openclean_pattern/align/distance/factory.py
openclean_pattern/align/distance/tde.py
openclean_pattern/align/distance/tree_edit.py
openclean_pattern/collect/__init__.py
openclean_pattern/collect/base.py
openclean_pattern/collect/cluster.py
openclean_pattern/collect/factory.py
openclean_pattern/collect/group.py
openclean_pattern/collect/neighbor.py
openclean_pattern/datatypes/__init__.py
openclean_pattern/datatypes/base.py
openclean_pattern/datatypes/resolver.py
openclean_pattern/evaluate/__init__.py
openclean_pattern/evaluate/evaluator.py
openclean_pattern/function/__init__.py
openclean_pattern/function/value.py
openclean_pattern/regex/__init__.py
openclean_pattern/regex/base.py
openclean_pattern/regex/compiler.py
openclean_pattern/regex/factory.py
openclean_pattern/tokenize/__init__.py
openclean_pattern/tokenize/factory.py
openclean_pattern/tokenize/prefix_tree.py
openclean_pattern/tokenize/regex.py
openclean_pattern/utils/__init__.py
openclean_pattern/utils/utils.py
openclean_pattern-0.0.1.dist-info/LICENSE
openclean_pattern-0.0.1.dist-info/METADATA
openclean_pattern-0.0.1.dist-info/WHEEL
openclean_pattern-0.0.1.dist-info/top_level.txt
openclean_pattern-0.0.1.dist-info/RECORD
