Metadata-Version: 2.1
Name: openclean-pattern
Version: 0.0.1
Summary: Library for pattern and anomalous pattern detection
Home-page: https://github.com/VIDA-NYU/openclean-pattern
Author: Munaf Qazi
Author-email: munaf.qazi@gmail.com
License: New BSD
Keywords: openclean_pattern,pattern detection
Platform: UNKNOWN
Classifier: License :: OSI Approved :: BSD License
Classifier: Operating System :: OS Independent
Classifier: Programming Language :: Python :: 3
Classifier: Programming Language :: Python :: 3.7
Classifier: Programming Language :: Python :: 3.8
Classifier: Programming Language :: Python
Requires-Dist: pandas
Requires-Dist: numpy
Requires-Dist: datamart-geo (>=0.2.1)
Requires-Dist: pygtrie (==2.3.3)
Requires-Dist: scikit-bio
Requires-Dist: openclean-core (>=0.3.0)
Provides-Extra: dev
Requires-Dist: flake8 ; extra == 'dev'
Requires-Dist: coverage (>=5.0) ; extra == 'dev'
Requires-Dist: pytest ; extra == 'dev'
Requires-Dist: pytest-cov ; extra == 'dev'
Provides-Extra: docs
Requires-Dist: Sphinx ; extra == 'docs'
Requires-Dist: sphinx-rtd-theme ; extra == 'docs'
Provides-Extra: tests
Requires-Dist: coverage (>=5.0) ; extra == 'tests'
Requires-Dist: pytest ; extra == 'tests'
Requires-Dist: pytest-cov ; extra == 'tests'
